[
  {
    "title": "Real-time Low-latency Music Source Separation using Hybrid Spectrogram-TasNet",
    "base_url": null,
    "title_page": null,
    "ieee_id": "10448381",
    "github": null,
    "web_page": null,
    "github_page": null,
    "colab": null,
    "modelscope": null,
    "gitee": null,
    "gitlab": null,
    "zenodo": null,
    "kaggle": null,
    "demo_page": null,
    "paper_thecvf": null,
    "paper_arxiv_id": "2402.17701",
    "paper_pdf": null,
    "paper_hal_science": null,
    "paper_researchgate": null,
    "paper_amazon": null,
    "youtube_id": null,
    "drive_google": null,
    "dropbox": null,
    "onedrive": null,
    "loom": null,
    "section": "Audio and Speech Source Separation"
  },
  {
    "title": "Music Source Separation with Band-Split RoPE Transformer",
    "base_url": null,
    "title_page": null,
    "ieee_id": "10446843",
    "github": null,
    "web_page": null,
    "github_page": null,
    "colab": null,
    "modelscope": null,
    "gitee": null,
    "gitlab": null,
    "zenodo": null,
    "kaggle": null,
    "demo_page": null,
    "paper_thecvf": null,
    "paper_arxiv_id": "2309.02612",
    "paper_pdf": null,
    "paper_hal_science": null,
    "paper_researchgate": null,
    "paper_amazon": null,
    "youtube_id": null,
    "drive_google": null,
    "dropbox": null,
    "onedrive": null,
    "loom": null,
    "section": "Audio and Speech Source Separation"
  },
  {
    "title": "Leveraging Sound Localization to Improve Continuous Speaker Separation",
    "base_url": null,
    "title_page": null,
    "ieee_id": "10446934",
    "github": null,
    "web_page": null,
    "github_page": null,
    "colab": null,
    "modelscope": null,
    "gitee": null,
    "gitlab": null,
    "zenodo": null,
    "kaggle": null,
    "demo_page": null,
    "paper_thecvf": null,
    "paper_arxiv_id": null,
    "paper_pdf": null,
    "paper_hal_science": null,
    "paper_researchgate": null,
    "paper_amazon": null,
    "youtube_id": null,
    "drive_google": null,
    "dropbox": null,
    "onedrive": null,
    "loom": null,
    "section": "Audio and Speech Source Separation"
  },
  {
    "title": "Boosting Unknown-number Speaker Separation with Transformer Decoder-based Attractor",
    "base_url": null,
    "title_page": null,
    "ieee_id": "10446032",
    "github": null,
    "web_page": null,
    "github_page": "https://42speech.github.io/septda/",
    "colab": null,
    "modelscope": null,
    "gitee": null,
    "gitlab": null,
    "zenodo": null,
    "kaggle": null,
    "demo_page": null,
    "paper_thecvf": null,
    "paper_arxiv_id": "2401.12473",
    "paper_pdf": null,
    "paper_hal_science": null,
    "paper_researchgate": null,
    "paper_amazon": null,
    "youtube_id": null,
    "drive_google": null,
    "dropbox": null,
    "onedrive": null,
    "loom": null,
    "section": "Audio and Speech Source Separation"
  },
  {
    "title": "GASS: Generalizing Audio Source Separation with Large-scale Data",
    "base_url": null,
    "title_page": null,
    "ieee_id": "10446601",
    "github": null,
    "web_page": null,
    "github_page": null,
    "colab": null,
    "modelscope": null,
    "gitee": null,
    "gitlab": null,
    "zenodo": null,
    "kaggle": null,
    "demo_page": null,
    "paper_thecvf": null,
    "paper_arxiv_id": "2310.00140",
    "paper_pdf": null,
    "paper_hal_science": null,
    "paper_researchgate": null,
    "paper_amazon": null,
    "youtube_id": null,
    "drive_google": null,
    "dropbox": null,
    "onedrive": null,
    "loom": null,
    "section": "Audio and Speech Source Separation"
  },
  {
    "title": "Audio Prompt Tuning for Universal Sound Separation",
    "base_url": null,
    "title_page": null,
    "ieee_id": "10447061",
    "github": null,
    "web_page": null,
    "github_page": null,
    "colab": null,
    "modelscope": null,
    "gitee": null,
    "gitlab": null,
    "zenodo": null,
    "kaggle": null,
    "demo_page": null,
    "paper_thecvf": null,
    "paper_arxiv_id": "2311.18399",
    "paper_pdf": null,
    "paper_hal_science": null,
    "paper_researchgate": null,
    "paper_amazon": null,
    "youtube_id": null,
    "drive_google": null,
    "dropbox": null,
    "onedrive": null,
    "loom": null,
    "section": "Audio and Speech Source Separation"
  }
]