[
  {
    "title": "Medical Vision-Language Representation Learning with Cross-Modal Multi-Teacher Contrastive Distillation",
    "base_url": null,
    "title_page": null,
    "ieee_id": "10447344",
    "github": null,
    "web_page": null,
    "github_page": null,
    "colab": null,
    "modelscope": null,
    "gitee": null,
    "gitlab": null,
    "zenodo": null,
    "kaggle": null,
    "demo_page": null,
    "paper_thecvf": null,
    "paper_arxiv_id": null,
    "paper_pdf": null,
    "paper_hal_science": null,
    "paper_researchgate": null,
    "paper_amazon": null,
    "youtube_id": null,
    "drive_google": null,
    "dropbox": null,
    "onedrive": null,
    "loom": null,
    "section": "Multimodal and Emerging Medical Signal Analysis"
  },
  {
    "title": "Localization and Tracking of Gold Nanoparticles Using mmWave FMCW Radar",
    "base_url": null,
    "title_page": null,
    "ieee_id": "10447738",
    "github": null,
    "web_page": null,
    "github_page": null,
    "colab": null,
    "modelscope": null,
    "gitee": null,
    "gitlab": null,
    "zenodo": null,
    "kaggle": null,
    "demo_page": null,
    "paper_thecvf": null,
    "paper_arxiv_id": null,
    "paper_pdf": null,
    "paper_hal_science": null,
    "paper_researchgate": null,
    "paper_amazon": null,
    "youtube_id": null,
    "drive_google": null,
    "dropbox": null,
    "onedrive": null,
    "loom": null,
    "section": "Multimodal and Emerging Medical Signal Analysis"
  },
  {
    "title": "Mosic: Multimodal Semantic Integrated Communication for Health Monitoring in IoT Scenarios",
    "base_url": null,
    "title_page": null,
    "ieee_id": "10446763",
    "github": null,
    "web_page": null,
    "github_page": null,
    "colab": null,
    "modelscope": null,
    "gitee": null,
    "gitlab": null,
    "zenodo": null,
    "kaggle": null,
    "demo_page": null,
    "paper_thecvf": null,
    "paper_arxiv_id": null,
    "paper_pdf": null,
    "paper_hal_science": null,
    "paper_researchgate": null,
    "paper_amazon": null,
    "youtube_id": null,
    "drive_google": null,
    "dropbox": null,
    "onedrive": null,
    "loom": null,
    "section": "Multimodal and Emerging Medical Signal Analysis"
  },
  {
    "title": "Neural2Speech: A Transfer Learning Framework for Neural-Driven Speech Reconstruction",
    "base_url": null,
    "title_page": null,
    "ieee_id": "10446614",
    "github": null,
    "web_page": null,
    "github_page": null,
    "colab": null,
    "modelscope": null,
    "gitee": null,
    "gitlab": null,
    "zenodo": null,
    "kaggle": null,
    "demo_page": null,
    "paper_thecvf": null,
    "paper_arxiv_id": "2310.04644",
    "paper_pdf": null,
    "paper_hal_science": null,
    "paper_researchgate": null,
    "paper_amazon": null,
    "youtube_id": null,
    "drive_google": null,
    "dropbox": null,
    "onedrive": null,
    "loom": null,
    "section": "Multimodal and Emerging Medical Signal Analysis"
  },
  {
    "title": "Do Self-Supervised Speech and Language Models Extract Similar Representations as Human Brain?",
    "base_url": null,
    "title_page": null,
    "ieee_id": "10446334",
    "github": null,
    "web_page": null,
    "github_page": null,
    "colab": null,
    "modelscope": null,
    "gitee": null,
    "gitlab": null,
    "zenodo": null,
    "kaggle": null,
    "demo_page": null,
    "paper_thecvf": null,
    "paper_arxiv_id": "2310.04645",
    "paper_pdf": null,
    "paper_hal_science": null,
    "paper_researchgate": null,
    "paper_amazon": null,
    "youtube_id": null,
    "drive_google": null,
    "dropbox": null,
    "onedrive": null,
    "loom": null,
    "section": "Multimodal and Emerging Medical Signal Analysis"
  },
  {
    "title": "Motion-Tolerant Radar-Based Heart Sound Detection",
    "base_url": null,
    "title_page": null,
    "ieee_id": "10448405",
    "github": null,
    "web_page": null,
    "github_page": null,
    "colab": null,
    "modelscope": null,
    "gitee": null,
    "gitlab": null,
    "zenodo": null,
    "kaggle": null,
    "demo_page": null,
    "paper_thecvf": null,
    "paper_arxiv_id": null,
    "paper_pdf": null,
    "paper_hal_science": null,
    "paper_researchgate": null,
    "paper_amazon": null,
    "youtube_id": null,
    "drive_google": null,
    "dropbox": null,
    "onedrive": null,
    "loom": null,
    "section": "Multimodal and Emerging Medical Signal Analysis"
  }
]