[
  {
    "title": "FPGNet: Single Image Deraining with High-Frequency Channel and Frequency Domain Prior Guidance",
    "base_url": null,
    "title_page": null,
    "ieee_id": "10446408",
    "github": null,
    "web_page": null,
    "github_page": null,
    "colab": null,
    "modelscope": null,
    "gitee": null,
    "gitlab": null,
    "zenodo": null,
    "kaggle": null,
    "demo_page": null,
    "paper_thecvf": null,
    "paper_arxiv_id": null,
    "paper_pdf": null,
    "paper_hal_science": null,
    "paper_researchgate": null,
    "paper_amazon": null,
    "youtube_id": null,
    "drive_google": null,
    "dropbox": null,
    "onedrive": null,
    "loom": null,
    "section": "Image Denoising"
  },
  {
    "title": "Latent Degradation Representation Constraint for Single Image Deraining",
    "base_url": null,
    "title_page": null,
    "ieee_id": "10447510",
    "github": null,
    "web_page": null,
    "github_page": null,
    "colab": null,
    "modelscope": null,
    "gitee": null,
    "gitlab": null,
    "zenodo": null,
    "kaggle": null,
    "demo_page": null,
    "paper_thecvf": null,
    "paper_arxiv_id": "2309.04780",
    "paper_pdf": null,
    "paper_hal_science": null,
    "paper_researchgate": null,
    "paper_amazon": null,
    "youtube_id": null,
    "drive_google": null,
    "dropbox": null,
    "onedrive": null,
    "loom": null,
    "section": "Image Denoising"
  },
  {
    "title": "Multi-Dimension Queried and Interacting Network for Stereo Image Deraining",
    "base_url": null,
    "title_page": null,
    "ieee_id": "10446127",
    "github": null,
    "web_page": null,
    "github_page": null,
    "colab": null,
    "modelscope": null,
    "gitee": null,
    "gitlab": null,
    "zenodo": null,
    "kaggle": null,
    "demo_page": null,
    "paper_thecvf": null,
    "paper_arxiv_id": null,
    "paper_pdf": null,
    "paper_hal_science": null,
    "paper_researchgate": null,
    "paper_amazon": null,
    "youtube_id": null,
    "drive_google": null,
    "dropbox": null,
    "onedrive": null,
    "loom": null,
    "section": "Image Denoising"
  },
  {
    "title": "Multi-Scale Fusion of Gated Neighborhood Attention Transformers for Single Image Deraining",
    "base_url": null,
    "title_page": null,
    "ieee_id": "10446762",
    "github": null,
    "web_page": null,
    "github_page": null,
    "colab": null,
    "modelscope": null,
    "gitee": null,
    "gitlab": null,
    "zenodo": null,
    "kaggle": null,
    "demo_page": null,
    "paper_thecvf": null,
    "paper_arxiv_id": null,
    "paper_pdf": null,
    "paper_hal_science": null,
    "paper_researchgate": null,
    "paper_amazon": null,
    "youtube_id": null,
    "drive_google": null,
    "dropbox": null,
    "onedrive": null,
    "loom": null,
    "section": "Image Denoising"
  },
  {
    "title": "CDCNet: A Fast and Lightweight Dehazing Network with Color Distortion Correction",
    "base_url": null,
    "title_page": null,
    "ieee_id": "10447111",
    "github": null,
    "web_page": null,
    "github_page": null,
    "colab": null,
    "modelscope": null,
    "gitee": null,
    "gitlab": null,
    "zenodo": null,
    "kaggle": null,
    "demo_page": null,
    "paper_thecvf": null,
    "paper_arxiv_id": null,
    "paper_pdf": null,
    "paper_hal_science": null,
    "paper_researchgate": null,
    "paper_amazon": null,
    "youtube_id": null,
    "drive_google": null,
    "dropbox": null,
    "onedrive": null,
    "loom": null,
    "section": "Image Denoising"
  },
  {
    "title": "A Two-Stage Dehazing Framework Based on Inverted Image Curve-Enhancement",
    "base_url": null,
    "title_page": null,
    "ieee_id": "10447314",
    "github": null,
    "web_page": null,
    "github_page": null,
    "colab": null,
    "modelscope": null,
    "gitee": null,
    "gitlab": null,
    "zenodo": null,
    "kaggle": null,
    "demo_page": null,
    "paper_thecvf": null,
    "paper_arxiv_id": null,
    "paper_pdf": null,
    "paper_hal_science": null,
    "paper_researchgate": null,
    "paper_amazon": null,
    "youtube_id": null,
    "drive_google": null,
    "dropbox": null,
    "onedrive": null,
    "loom": null,
    "section": "Image Denoising"
  },
  {
    "title": "Deep Unrolling Network for SAR Image Despeckling",
    "base_url": null,
    "title_page": null,
    "ieee_id": "10447792",
    "github": null,
    "web_page": null,
    "github_page": null,
    "colab": null,
    "modelscope": null,
    "gitee": null,
    "gitlab": null,
    "zenodo": null,
    "kaggle": null,
    "demo_page": null,
    "paper_thecvf": null,
    "paper_arxiv_id": null,
    "paper_pdf": null,
    "paper_hal_science": null,
    "paper_researchgate": null,
    "paper_amazon": null,
    "youtube_id": null,
    "drive_google": null,
    "dropbox": null,
    "onedrive": null,
    "loom": null,
    "section": "Image Denoising"
  },
  {
    "title": "RVDNet: A Two-Stage Network for Real-World Video Desnowing with Domain Adaptation",
    "base_url": null,
    "title_page": null,
    "ieee_id": "10448423",
    "github": null,
    "web_page": null,
    "github_page": null,
    "colab": null,
    "modelscope": null,
    "gitee": null,
    "gitlab": null,
    "zenodo": null,
    "kaggle": null,
    "demo_page": null,
    "paper_thecvf": null,
    "paper_arxiv_id": null,
    "paper_pdf": null,
    "paper_hal_science": null,
    "paper_researchgate": null,
    "paper_amazon": null,
    "youtube_id": null,
    "drive_google": null,
    "dropbox": null,
    "onedrive": null,
    "loom": null,
    "section": "Image Denoising"
  },
  {
    "title": "Beyond the Snowfall: Enhancing Snowy Day Object Detection Through Progressive Restoration and Multi-Feature Fusion",
    "base_url": null,
    "title_page": null,
    "ieee_id": "10446306",
    "github": null,
    "web_page": null,
    "github_page": null,
    "colab": null,
    "modelscope": null,
    "gitee": null,
    "gitlab": null,
    "zenodo": null,
    "kaggle": null,
    "demo_page": null,
    "paper_thecvf": null,
    "paper_arxiv_id": null,
    "paper_pdf": null,
    "paper_hal_science": null,
    "paper_researchgate": null,
    "paper_amazon": null,
    "youtube_id": null,
    "drive_google": null,
    "dropbox": null,
    "onedrive": null,
    "loom": null,
    "section": "Image Denoising"
  },
  {
    "title": "BFRFormer: Transformer-Based Generator for Real-World Blind Face Restoration",
    "base_url": null,
    "title_page": null,
    "ieee_id": "10446939",
    "github": null,
    "web_page": null,
    "github_page": null,
    "colab": null,
    "modelscope": null,
    "gitee": null,
    "gitlab": null,
    "zenodo": null,
    "kaggle": null,
    "demo_page": null,
    "paper_thecvf": null,
    "paper_arxiv_id": "2402.18811",
    "paper_pdf": null,
    "paper_hal_science": null,
    "paper_researchgate": null,
    "paper_amazon": null,
    "youtube_id": null,
    "drive_google": null,
    "dropbox": null,
    "onedrive": null,
    "loom": null,
    "section": "Image Denoising"
  },
  {
    "title": "SDRNet: Saliency-Guided Dynamic Restoration Network for Rain and Haze Removal in Nighttime Images",
    "base_url": null,
    "title_page": null,
    "ieee_id": "10447635",
    "github": null,
    "web_page": null,
    "github_page": null,
    "colab": null,
    "modelscope": null,
    "gitee": null,
    "gitlab": null,
    "zenodo": null,
    "kaggle": null,
    "demo_page": null,
    "paper_thecvf": null,
    "paper_arxiv_id": null,
    "paper_pdf": null,
    "paper_hal_science": null,
    "paper_researchgate": null,
    "paper_amazon": null,
    "youtube_id": null,
    "drive_google": null,
    "dropbox": null,
    "onedrive": null,
    "loom": null,
    "section": "Image Denoising"
  },
  {
    "title": "Toward Sufficient Spatial-Frequency Interaction for Gradient-Aware Underwater Image Enhancement",
    "base_url": null,
    "title_page": null,
    "ieee_id": "10448182",
    "github": null,
    "web_page": null,
    "github_page": null,
    "colab": null,
    "modelscope": null,
    "gitee": null,
    "gitlab": null,
    "zenodo": null,
    "kaggle": null,
    "demo_page": null,
    "paper_thecvf": null,
    "paper_arxiv_id": "2309.04089",
    "paper_pdf": null,
    "paper_hal_science": null,
    "paper_researchgate": null,
    "paper_amazon": null,
    "youtube_id": null,
    "drive_google": null,
    "dropbox": null,
    "onedrive": null,
    "loom": null,
    "section": "Image Denoising"
  }
]