[
  {
    "title": "Unravel Anomalies: an End-to-End Seasonal-Trend Decomposition Approach for Time Series Anomaly Detection",
    "base_url": null,
    "title_page": null,
    "ieee_id": "10446482",
    "github": null,
    "web_page": null,
    "github_page": null,
    "colab": null,
    "modelscope": null,
    "gitee": null,
    "gitlab": null,
    "zenodo": null,
    "kaggle": null,
    "demo_page": null,
    "paper_thecvf": null,
    "paper_arxiv_id": "2310.00268",
    "paper_pdf": null,
    "paper_hal_science": null,
    "paper_researchgate": null,
    "paper_amazon": null,
    "youtube_id": null,
    "drive_google": null,
    "dropbox": null,
    "onedrive": null,
    "loom": null,
    "section": "Machine Learning for Time Series Analysis"
  },
  {
    "title": "Multivariate Time Series Forecasting with Causal-Temporal Attention Network",
    "base_url": null,
    "title_page": null,
    "ieee_id": "10448031",
    "github": null,
    "web_page": null,
    "github_page": null,
    "colab": null,
    "modelscope": null,
    "gitee": null,
    "gitlab": null,
    "zenodo": null,
    "kaggle": null,
    "demo_page": null,
    "paper_thecvf": null,
    "paper_arxiv_id": null,
    "paper_pdf": null,
    "paper_hal_science": null,
    "paper_researchgate": null,
    "paper_amazon": null,
    "youtube_id": null,
    "drive_google": null,
    "dropbox": null,
    "onedrive": null,
    "loom": null,
    "section": "Machine Learning for Time Series Analysis"
  },
  {
    "title": "TreeMIL: A Multi-instance Learning Framework for Time Series Anomaly Detection with Inexact Supervision",
    "base_url": null,
    "title_page": null,
    "ieee_id": "10447536",
    "github": "fly-orange/TreeMIL",
    "web_page": null,
    "github_page": null,
    "colab": null,
    "modelscope": null,
    "gitee": null,
    "gitlab": null,
    "zenodo": null,
    "kaggle": null,
    "demo_page": null,
    "paper_thecvf": null,
    "paper_arxiv_id": "2401.11235",
    "paper_pdf": null,
    "paper_hal_science": null,
    "paper_researchgate": null,
    "paper_amazon": null,
    "youtube_id": null,
    "drive_google": null,
    "dropbox": null,
    "onedrive": null,
    "loom": null,
    "section": "Machine Learning for Time Series Analysis"
  },
  {
    "title": "DCS: Debiased Contrastive Learning with Weak Supervision for Time Series Classification",
    "base_url": null,
    "title_page": null,
    "ieee_id": "10446381",
    "github": null,
    "web_page": null,
    "github_page": null,
    "colab": null,
    "modelscope": null,
    "gitee": null,
    "gitlab": null,
    "zenodo": null,
    "kaggle": null,
    "demo_page": null,
    "paper_thecvf": null,
    "paper_arxiv_id": null,
    "paper_pdf": null,
    "paper_hal_science": null,
    "paper_researchgate": null,
    "paper_amazon": null,
    "youtube_id": null,
    "drive_google": null,
    "dropbox": null,
    "onedrive": null,
    "loom": null,
    "section": "Machine Learning for Time Series Analysis"
  },
  {
    "title": "Skip-Step Contrastive Predictive Coding for Time Series Anomaly Detection",
    "base_url": null,
    "title_page": null,
    "ieee_id": "10447104",
    "github": null,
    "web_page": null,
    "github_page": null,
    "colab": null,
    "modelscope": null,
    "gitee": null,
    "gitlab": null,
    "zenodo": null,
    "kaggle": null,
    "demo_page": null,
    "paper_thecvf": null,
    "paper_arxiv_id": null,
    "paper_pdf": null,
    "paper_hal_science": null,
    "paper_researchgate": null,
    "paper_amazon": null,
    "youtube_id": null,
    "drive_google": null,
    "dropbox": null,
    "onedrive": null,
    "loom": null,
    "section": "Machine Learning for Time Series Analysis"
  },
  {
    "title": "Enhancing Short-and Long-Term Sea Surface Temperature Forecasting with a Static and Dynamic Learnable Personalized Graph Convolution Network",
    "base_url": null,
    "title_page": null,
    "ieee_id": "10448135",
    "github": null,
    "web_page": null,
    "github_page": null,
    "colab": null,
    "modelscope": null,
    "gitee": null,
    "gitlab": null,
    "zenodo": null,
    "kaggle": null,
    "demo_page": null,
    "paper_thecvf": null,
    "paper_arxiv_id": null,
    "paper_pdf": null,
    "paper_hal_science": null,
    "paper_researchgate": null,
    "paper_amazon": null,
    "youtube_id": null,
    "drive_google": null,
    "dropbox": null,
    "onedrive": null,
    "loom": null,
    "section": "Machine Learning for Time Series Analysis"
  }
]